yzuid/__init__.py
yzuid/__main__.py
yzuid/converter/__init__.py
yzuid/id/__init__.py
yzuid/id/_id.py
yzuid/id/_id_meta.py
yzuid/id/id_service.py
yzuid/populator/__init__.py
yzuid/populator/atomic_populator.py
yzuid/populator/lock_populator.py
yzuid/populator/sync_populator.py
yzuid/provider/__init__.py
yzuid/utils/__init__.py
yzuid/utils/time_util.py
yzuid-0.1.0.dist-info/LICENSE
yzuid-0.1.0.dist-info/METADATA
yzuid-0.1.0.dist-info/WHEEL
yzuid-0.1.0.dist-info/top_level.txt
yzuid-0.1.0.dist-info/RECORD
