Metadata-Version: 2.1
Name: yzuid
Version: 0.1.0
Summary: An ID generator for distributed microservices
Home-page: https://github.com/fu477521/yzuid
Author: cml
Author-email: fu477521@163.com
License: UNKNOWN
Platform: UNKNOWN
Classifier: Programming Language :: Python :: 3
Classifier: License :: OSI Approved :: MIT License
Classifier: Operating System :: OS Independent
Requires-Python: >=3.6
